{
  "$schema": "https://raw.githubusercontent.com/spdx/spdx-spec/v2.2.1/schemas/spdx-schema.json",
  "spdxVersion": "SPDX-2.2",
  "dataLicense": "CC0-1.0",
  "SPDXID": "SPDXRef-DOCUMENT",
  "documentNamespace": "https://spdx.org/spdxdocs/wxpython-x64-windows-4.2.0#14-f9c135f6-f62e-4c0d-a15f-f888d841edc3",
  "name": "wxpython:x64-windows@4.2.0#14 2755f46124ffd28e83282be98a6a2aad629f8a7c32af7aba011d54b95ca5a8fe",
  "creationInfo": {
    "creators": [
      "Tool: vcpkg-8a83681f921b10d86ae626fd833c253f4f8c355b"
    ],
    "created": "2024-04-25T05:08:07Z"
  },
  "relationships": [
    {
      "spdxElementId": "SPDXRef-port",
      "relationshipType": "GENERATES",
      "relatedSpdxElement": "SPDXRef-binary"
    },
    {
      "spdxElementId": "SPDXRef-port",
      "relationshipType": "CONTAINS",
      "relatedSpdxElement": "SPDXRef-file-0"
    },
    {
      "spdxElementId": "SPDXRef-port",
      "relationshipType": "CONTAINS",
      "relatedSpdxElement": "SPDXRef-file-1"
    },
    {
      "spdxElementId": "SPDXRef-port",
      "relationshipType": "CONTAINS",
      "relatedSpdxElement": "SPDXRef-file-2"
    },
    {
      "spdxElementId": "SPDXRef-port",
      "relationshipType": "CONTAINS",
      "relatedSpdxElement": "SPDXRef-file-3"
    },
    {
      "spdxElementId": "SPDXRef-port",
      "relationshipType": "CONTAINS",
      "relatedSpdxElement": "SPDXRef-file-4"
    },
    {
      "spdxElementId": "SPDXRef-port",
      "relationshipType": "CONTAINS",
      "relatedSpdxElement": "SPDXRef-file-5"
    },
    {
      "spdxElementId": "SPDXRef-port",
      "relationshipType": "CONTAINS",
      "relatedSpdxElement": "SPDXRef-file-6"
    },
    {
      "spdxElementId": "SPDXRef-port",
      "relationshipType": "CONTAINS",
      "relatedSpdxElement": "SPDXRef-file-7"
    },
    {
      "spdxElementId": "SPDXRef-port",
      "relationshipType": "CONTAINS",
      "relatedSpdxElement": "SPDXRef-file-8"
    },
    {
      "spdxElementId": "SPDXRef-binary",
      "relationshipType": "GENERATED_FROM",
      "relatedSpdxElement": "SPDXRef-port"
    },
    {
      "spdxElementId": "SPDXRef-file-0",
      "relationshipType": "CONTAINED_BY",
      "relatedSpdxElement": "SPDXRef-port"
    },
    {
      "spdxElementId": "SPDXRef-file-1",
      "relationshipType": "CONTAINED_BY",
      "relatedSpdxElement": "SPDXRef-port"
    },
    {
      "spdxElementId": "SPDXRef-file-2",
      "relationshipType": "CONTAINED_BY",
      "relatedSpdxElement": "SPDXRef-port"
    },
    {
      "spdxElementId": "SPDXRef-file-3",
      "relationshipType": "CONTAINED_BY",
      "relatedSpdxElement": "SPDXRef-port"
    },
    {
      "spdxElementId": "SPDXRef-file-4",
      "relationshipType": "CONTAINED_BY",
      "relatedSpdxElement": "SPDXRef-port"
    },
    {
      "spdxElementId": "SPDXRef-file-5",
      "relationshipType": "CONTAINED_BY",
      "relatedSpdxElement": "SPDXRef-port"
    },
    {
      "spdxElementId": "SPDXRef-file-6",
      "relationshipType": "CONTAINED_BY",
      "relatedSpdxElement": "SPDXRef-port"
    },
    {
      "spdxElementId": "SPDXRef-file-7",
      "relationshipType": "CONTAINED_BY",
      "relatedSpdxElement": "SPDXRef-port"
    },
    {
      "spdxElementId": "SPDXRef-file-8",
      "relationshipType": "CONTAINED_BY",
      "relatedSpdxElement": "SPDXRef-port"
    }
  ],
  "packages": [
    {
      "name": "wxpython",
      "SPDXID": "SPDXRef-port",
      "versionInfo": "4.2.0#14",
      "downloadLocation": "git+https://gitlab.com/kicad/packaging/kicad-vcpkg-registry.git@e8ee09e9cc0869fdf74d39ad309701ca6abdda4b",
      "homepage": "https://github.com/wxWidgets/phoenix",
      "licenseConcluded": "NOASSERTION",
      "licenseDeclared": "NOASSERTION",
      "copyrightText": "NOASSERTION",
      "description": "Python library that allows creating wxWidget interfaces from python",
      "comment": "This is the port (recipe) consumed by vcpkg."
    },
    {
      "name": "wxpython:x64-windows",
      "SPDXID": "SPDXRef-binary",
      "versionInfo": "2755f46124ffd28e83282be98a6a2aad629f8a7c32af7aba011d54b95ca5a8fe",
      "downloadLocation": "NONE",
      "licenseConcluded": "NOASSERTION",
      "licenseDeclared": "NOASSERTION",
      "copyrightText": "NOASSERTION",
      "comment": "This is a binary package built by vcpkg."
    },
    {
      "SPDXID": "SPDXRef-resource-1",
      "name": "wxWidgets/phoenix",
      "downloadLocation": "git+https://github.com/wxWidgets/phoenix@fb335e8cc92bc7719e5181385b56f599b993631f",
      "licenseConcluded": "NOASSERTION",
      "licenseDeclared": "NOASSERTION",
      "copyrightText": "NOASSERTION",
      "checksums": [
        {
          "algorithm": "SHA512",
          "checksumValue": "6a952969442f95ba4b9cf0505f1f03c683324d4b5d05299dc814995fb7dd58c0cf9ce28c6d1409eb26ce41779a964e7fa1553d58969ad02b0573d962412c97ed"
        }
      ]
    }
  ],
  "files": [
    {
      "fileName": "./C:/Users/ws/AppData/Local/vcpkg/registries/git-trees/e8ee09e9cc0869fdf74d39ad309701ca6abdda4b/cmake/__version__.py.in",
      "SPDXID": "SPDXRef-file-0",
      "checksums": [
        {
          "algorithm": "SHA256",
          "checksumValue": "6c524e2fec11ef65497365666feca1bd156d26d23badf1550a47d524ca2df869"
        }
      ],
      "licenseConcluded": "NOASSERTION",
      "copyrightText": "NOASSERTION"
    },
    {
      "fileName": "./C:/Users/ws/AppData/Local/vcpkg/registries/git-trees/e8ee09e9cc0869fdf74d39ad309701ca6abdda4b/CMakeLists.txt",
      "SPDXID": "SPDXRef-file-1",
      "checksums": [
        {
          "algorithm": "SHA256",
          "checksumValue": "ec8bcdae9b2d023c65be3c1137fd71465410388e0f9d64287b901b8ee512e610"
        }
      ],
      "licenseConcluded": "NOASSERTION",
      "copyrightText": "NOASSERTION"
    },
    {
      "fileName": "./C:/Users/ws/AppData/Local/vcpkg/registries/git-trees/e8ee09e9cc0869fdf74d39ad309701ca6abdda4b/copyright",
      "SPDXID": "SPDXRef-file-2",
      "checksums": [
        {
          "algorithm": "SHA256",
          "checksumValue": "e8453be21aea2b7cc9a39d5b0475190bbfa0a60605b4178377590b94d9c43eae"
        }
      ],
      "licenseConcluded": "NOASSERTION",
      "copyrightText": "NOASSERTION"
    },
    {
      "fileName": "./C:/Users/ws/AppData/Local/vcpkg/registries/git-trees/e8ee09e9cc0869fdf74d39ad309701ca6abdda4b/ignore-CreateSurface-glcanvas.patch",
      "SPDXID": "SPDXRef-file-3",
      "checksums": [
        {
          "algorithm": "SHA256",
          "checksumValue": "34c9e7880a5ca772190f57bd976be91b2929058690756bdbbc2be1808a0b7d13"
        }
      ],
      "licenseConcluded": "NOASSERTION",
      "copyrightText": "NOASSERTION"
    },
    {
      "fileName": "./C:/Users/ws/AppData/Local/vcpkg/registries/git-trees/e8ee09e9cc0869fdf74d39ad309701ca6abdda4b/ignore-osx-textctl.patch",
      "SPDXID": "SPDXRef-file-4",
      "checksums": [
        {
          "algorithm": "SHA256",
          "checksumValue": "251719a811d6e29c00649692db817dfe7c8649d30ad4616691ee87bef7e404d6"
        }
      ],
      "licenseConcluded": "NOASSERTION",
      "copyrightText": "NOASSERTION"
    },
    {
      "fileName": "./C:/Users/ws/AppData/Local/vcpkg/registries/git-trees/e8ee09e9cc0869fdf74d39ad309701ca6abdda4b/ignore-stackwalker-GetAssertStackTrace.patch",
      "SPDXID": "SPDXRef-file-5",
      "checksums": [
        {
          "algorithm": "SHA256",
          "checksumValue": "f1aab9d7a827e0273d5acbb00d130db3020e982ed1c23c2715c56c32de6537f4"
        }
      ],
      "licenseConcluded": "NOASSERTION",
      "copyrightText": "NOASSERTION"
    },
    {
      "fileName": "./C:/Users/ws/AppData/Local/vcpkg/registries/git-trees/e8ee09e9cc0869fdf74d39ad309701ca6abdda4b/patch-sip-gc.patch",
      "SPDXID": "SPDXRef-file-6",
      "checksums": [
        {
          "algorithm": "SHA256",
          "checksumValue": "37453050d8d6c04fac439954246acb6d08c9072682125ab5f048219ffbbd19e5"
        }
      ],
      "licenseConcluded": "NOASSERTION",
      "copyrightText": "NOASSERTION"
    },
    {
      "fileName": "./C:/Users/ws/AppData/Local/vcpkg/registries/git-trees/e8ee09e9cc0869fdf74d39ad309701ca6abdda4b/portfile.cmake",
      "SPDXID": "SPDXRef-file-7",
      "checksums": [
        {
          "algorithm": "SHA256",
          "checksumValue": "ba3c875ebb2d28798542e89fa8650f3c4d5535f415e1914878ff97cf45a6dd32"
        }
      ],
      "licenseConcluded": "NOASSERTION",
      "copyrightText": "NOASSERTION"
    },
    {
      "fileName": "./C:/Users/ws/AppData/Local/vcpkg/registries/git-trees/e8ee09e9cc0869fdf74d39ad309701ca6abdda4b/vcpkg.json",
      "SPDXID": "SPDXRef-file-8",
      "checksums": [
        {
          "algorithm": "SHA256",
          "checksumValue": "c225a04867732db43c11c57a37894fd8a25592addc8853f775ae8c10a0525694"
        }
      ],
      "licenseConcluded": "NOASSERTION",
      "copyrightText": "NOASSERTION"
    }
  ]
}
